kunsplash/__init__.py
kunsplash/unsplash.py
kunsplash/models/__init__.py
kunsplash/models/image_urls.py
kunsplash/models/unsplash_image.py
kunsplash-0.0.2.dist-info/METADATA
kunsplash-0.0.2.dist-info/WHEEL
kunsplash-0.0.2.dist-info/top_level.txt
kunsplash-0.0.2.dist-info/RECORD
